githubactioncontexthelper/__init__.py
githubactioncontexthelper/__version__.py
githubactioncontexthelper/contexthandler.py
githubactioncontexthelper/githubactioncontext.py
githubactioncontexthelper-0.0.7.dist-info/LICENSE
githubactioncontexthelper-0.0.7.dist-info/METADATA
githubactioncontexthelper-0.0.7.dist-info/WHEEL
githubactioncontexthelper-0.0.7.dist-info/top_level.txt
githubactioncontexthelper-0.0.7.dist-info/RECORD
