Metadata-Version: 2.1
Name: githubactioncontexthelper
Version: 0.0.7
Summary: githubactioncontexthelper - GitHub Action Context Helper
Home-page: https://github.com/mlspec/githubactioncontexthelper
Author: David Aronchick
Author-email: aronchick@gmail.com
License: Apache 2.0
Keywords: package development template
Platform: UNKNOWN
Classifier: Development Status :: 4 - Beta
Classifier: Intended Audience :: Developers
Classifier: Programming Language :: Python :: 3.8
Requires-Python: >=3.8.*
Requires-Dist: setuptools
